<?xml version="1.0" encoding="UTF-8"?><record_update table="sc_cat_item_producer">
    <sc_cat_item_producer action="DELETE">
        <access_type>restricted</access_type>
        <active>true</active>
        <allow_edit>false</allow_edit>
        <availability>on_desktop</availability>
        <billable>false</billable>
        <can_cancel>false</can_cancel>
        <category/>
        <checked_out/>
        <cost>0</cost>
        <custom_cart/>
        <delivery_plan display_value="DEFAULT">523da512c611228900811a37c97c2014</delivery_plan>
        <delivery_plan_script/>
        <delivery_time>1970-01-03 00:00:00</delivery_time>
        <description/>
        <display_price_property>non_zero</display_price_property>
        <entitlement_script/>
        <flow_designer_flow/>
        <fulfillment_automation_level>unspecified</fulfillment_automation_level>
        <group/>
        <hide_sp>false</hide_sp>
        <icon>15199e89c3b726107e68b41ed401313a</icon>
        <ignore_price>true</ignore_price>
        <image/>
        <location/>
        <make_item_non_conversational>false</make_item_non_conversational>
        <mandatory_attachment>false</mandatory_attachment>
        <meta/>
        <mobile_hide_price>false</mobile_hide_price>
        <mobile_picture/>
        <mobile_picture_type>use_desktop_picture</mobile_picture_type>
        <model/>
        <name>Azure Synapse Analytics workspace</name>
        <no_attachment_v2>true</no_attachment_v2>
        <no_cart>false</no_cart>
        <no_cart_v2>false</no_cart_v2>
        <no_delivery_time_v2>false</no_delivery_time_v2>
        <no_order>false</no_order>
        <no_order_now>false</no_order_now>
        <no_proceed_checkout>false</no_proceed_checkout>
        <no_quantity>false</no_quantity>
        <no_quantity_v2>false</no_quantity_v2>
        <no_save_as_draft>true</no_save_as_draft>
        <no_search>false</no_search>
        <no_wishlist_v2>false</no_wishlist_v2>
        <omit_price>false</omit_price>
        <order>0</order>
        <ordered_item_link/>
        <owner display_value="">system</owner>
        <picture>d5199e89c3b726107e68b41ed401313b</picture>
        <post_insert_script><![CDATA[/**
* This script is executed after the record is generated. 
* `current` Is the GlideRecord produced by Record Producer. Use `current.update()` to update the record
* To access the variables, use `producer.var1` where var1 is the name of the variable
* To access the Record Producer use `cat_item`
*/]]></post_insert_script>
        <preview>JavaScript: popupOpenStandard("com.glideapp.servicecatalog_cat_item_view.do?v=1&amp;sysparm_id=59199e89c3b726107e68b41ed401313c&amp;sysparm_preview=true", "summary");</preview>
        <price>0</price>
        <published_ref/>
        <recurring_frequency/>
        <redirect_url>generated_record</redirect_url>
        <request_method/>
        <roles/>
        <save_options/>
        <save_script><![CDATA[/**
* This script is executed at every step save in Catalog Builder. 
* This script is executed before `Script` is executed.
* `current` Is the GlideRecord produced by Record Producer. 
* To access the variables, use `producer.var1` where var1 is the name of the variable
* To access the Record Producer use `cat_item`
*/]]></save_script>
        <sc_catalogs/>
        <sc_ic_item_staging/>
        <sc_ic_version/>
        <sc_template/>
        <script><![CDATA[current.project = producer.selectedProject;
current.environment = producer.selectedEnvironment;]]></script>
        <short_description>Azure Synapse Analytics workspace</short_description>
        <show_variable_help_on_load>false</show_variable_help_on_load>
        <start_closed>false</start_closed>
        <state/>
        <sys_class_name>sc_cat_item_producer</sys_class_name>
        <sys_created_by>system</sys_created_by>
        <sys_created_on>2025-09-03 20:28:11</sys_created_on>
        <sys_id>59199e89c3b726107e68b41ed401313c</sys_id>
        <sys_mod_count>36</sys_mod_count>
        <sys_name>Azure Synapse Analytics workspace</sys_name>
        <sys_package display_value="Brainboard" source="x_854636_b_board">7062797e832822103e53f065eeaad32b</sys_package>
        <sys_policy/>
        <sys_scope display_value="Brainboard">7062797e832822103e53f065eeaad32b</sys_scope>
        <sys_update_name>sc_cat_item_producer_59199e89c3b726107e68b41ed401313c</sys_update_name>
        <sys_updated_by>system</sys_updated_by>
        <sys_updated_on>2025-09-04 20:33:30</sys_updated_on>
        <table_name>x_854636_b_board_clone_template_task</table_name>
        <taxonomy_topic/>
        <template/>
        <template_manager_roles/>
        <type>item</type>
        <use_sc_layout>true</use_sc_layout>
        <vendor/>
        <version>37</version>
        <view/>
        <visible_bundle>true</visible_bundle>
        <visible_guide>true</visible_guide>
        <visible_standalone>true</visible_standalone>
        <workflow/>
    </sc_cat_item_producer>
    <sys_translated_text action="DELETE" query="documentkey=59199e89c3b726107e68b41ed401313c"/>
    <fx_price action="DELETE" query="id=59199e89c3b726107e68b41ed401313c"/>
    <fx_price action="DELETE">
        <amount>0</amount>
        <currency display_value="USD">USD</currency>
        <field>price</field>
        <id>59199e89c3b726107e68b41ed401313c</id>
        <parent/>
        <reference_amount>0</reference_amount>
        <reference_currency display_value="USD">USD</reference_currency>
        <sys_created_by>system</sys_created_by>
        <sys_created_on>2025-09-03 20:28:11</sys_created_on>
        <sys_id>19199e89c3b726107e68b41ed401313f</sys_id>
        <sys_mod_count>0</sys_mod_count>
        <sys_updated_by>system</sys_updated_by>
        <sys_updated_on>2025-09-03 20:28:11</sys_updated_on>
        <table>sc_cat_item_producer</table>
        <type>calculated</type>
    </fx_price>
    <sys_update_version action="INSERT_OR_UPDATE">
        <action>DELETE</action>
        <application display_value="Brainboard">7062797e832822103e53f065eeaad32b</application>
        <file_path/>
        <instance_id>2fa811a01b0679d4fe1b43f4bd4bcb98</instance_id>
        <instance_name>dev190630</instance_name>
        <name>sc_cat_item_producer_59199e89c3b726107e68b41ed401313c</name>
        <payload>&lt;?xml version="1.0" encoding="UTF-8"?&gt;&lt;record_update table="sc_cat_item_producer"&gt;&lt;sc_cat_item_producer action="INSERT_OR_UPDATE"&gt;&lt;access_type&gt;restricted&lt;/access_type&gt;&lt;active&gt;true&lt;/active&gt;&lt;allow_edit&gt;false&lt;/allow_edit&gt;&lt;availability&gt;on_desktop&lt;/availability&gt;&lt;billable&gt;false&lt;/billable&gt;&lt;can_cancel&gt;false&lt;/can_cancel&gt;&lt;category/&gt;&lt;checked_out/&gt;&lt;cost&gt;0&lt;/cost&gt;&lt;custom_cart/&gt;&lt;delivery_plan display_value="DEFAULT"&gt;523da512c611228900811a37c97c2014&lt;/delivery_plan&gt;&lt;delivery_plan_script/&gt;&lt;delivery_time&gt;1970-01-03 00:00:00&lt;/delivery_time&gt;&lt;description/&gt;&lt;display_price_property&gt;non_zero&lt;/display_price_property&gt;&lt;entitlement_script/&gt;&lt;flow_designer_flow/&gt;&lt;fulfillment_automation_level&gt;unspecified&lt;/fulfillment_automation_level&gt;&lt;group/&gt;&lt;hide_sp&gt;false&lt;/hide_sp&gt;&lt;icon&gt;15199e89c3b726107e68b41ed401313a&lt;/icon&gt;&lt;ignore_price&gt;true&lt;/ignore_price&gt;&lt;image/&gt;&lt;location/&gt;&lt;make_item_non_conversational&gt;false&lt;/make_item_non_conversational&gt;&lt;mandatory_attachment&gt;false&lt;/mandatory_attachment&gt;&lt;meta/&gt;&lt;mobile_hide_price&gt;false&lt;/mobile_hide_price&gt;&lt;mobile_picture/&gt;&lt;mobile_picture_type&gt;use_desktop_picture&lt;/mobile_picture_type&gt;&lt;model/&gt;&lt;name&gt;Azure Synapse Analytics workspace&lt;/name&gt;&lt;no_attachment_v2&gt;true&lt;/no_attachment_v2&gt;&lt;no_cart&gt;false&lt;/no_cart&gt;&lt;no_cart_v2&gt;false&lt;/no_cart_v2&gt;&lt;no_delivery_time_v2&gt;false&lt;/no_delivery_time_v2&gt;&lt;no_order&gt;false&lt;/no_order&gt;&lt;no_order_now&gt;false&lt;/no_order_now&gt;&lt;no_proceed_checkout&gt;false&lt;/no_proceed_checkout&gt;&lt;no_quantity&gt;false&lt;/no_quantity&gt;&lt;no_quantity_v2&gt;false&lt;/no_quantity_v2&gt;&lt;no_save_as_draft&gt;true&lt;/no_save_as_draft&gt;&lt;no_search&gt;false&lt;/no_search&gt;&lt;no_wishlist_v2&gt;false&lt;/no_wishlist_v2&gt;&lt;omit_price&gt;false&lt;/omit_price&gt;&lt;order&gt;0&lt;/order&gt;&lt;ordered_item_link/&gt;&lt;owner display_value=""&gt;system&lt;/owner&gt;&lt;picture&gt;d5199e89c3b726107e68b41ed401313b&lt;/picture&gt;&lt;post_insert_script&gt;&lt;![CDATA[/**
* This script is executed after the record is generated. 
* `current` Is the GlideRecord produced by Record Producer. Use `current.update()` to update the record
* To access the variables, use `producer.var1` where var1 is the name of the variable
* To access the Record Producer use `cat_item`
*/]]&gt;&lt;/post_insert_script&gt;&lt;preview&gt;JavaScript: popupOpenStandard("com.glideapp.servicecatalog_cat_item_view.do?v=1&amp;amp;sysparm_id=59199e89c3b726107e68b41ed401313c&amp;amp;sysparm_preview=true", "summary");&lt;/preview&gt;&lt;price&gt;0&lt;/price&gt;&lt;published_ref/&gt;&lt;recurring_frequency/&gt;&lt;redirect_url&gt;generated_record&lt;/redirect_url&gt;&lt;request_method/&gt;&lt;roles/&gt;&lt;save_options/&gt;&lt;save_script&gt;&lt;![CDATA[/**
* This script is executed at every step save in Catalog Builder. 
* This script is executed before `Script` is executed.
* `current` Is the GlideRecord produced by Record Producer. 
* To access the variables, use `producer.var1` where var1 is the name of the variable
* To access the Record Producer use `cat_item`
*/]]&gt;&lt;/save_script&gt;&lt;sc_catalogs/&gt;&lt;sc_ic_item_staging/&gt;&lt;sc_ic_version/&gt;&lt;sc_template/&gt;&lt;script&gt;&lt;![CDATA[current.project = producer.selectedProject;
current.environment = producer.selectedEnvironment;]]&gt;&lt;/script&gt;&lt;short_description&gt;Azure Synapse Analytics workspace&lt;/short_description&gt;&lt;show_variable_help_on_load&gt;false&lt;/show_variable_help_on_load&gt;&lt;start_closed&gt;false&lt;/start_closed&gt;&lt;state/&gt;&lt;sys_class_name&gt;sc_cat_item_producer&lt;/sys_class_name&gt;&lt;sys_created_by&gt;system&lt;/sys_created_by&gt;&lt;sys_created_on&gt;2025-09-03 20:28:11&lt;/sys_created_on&gt;&lt;sys_id&gt;59199e89c3b726107e68b41ed401313c&lt;/sys_id&gt;&lt;sys_mod_count&gt;36&lt;/sys_mod_count&gt;&lt;sys_name&gt;Azure Synapse Analytics workspace&lt;/sys_name&gt;&lt;sys_package display_value="Brainboard" source="x_854636_b_board"&gt;7062797e832822103e53f065eeaad32b&lt;/sys_package&gt;&lt;sys_policy/&gt;&lt;sys_scope display_value="Brainboard"&gt;7062797e832822103e53f065eeaad32b&lt;/sys_scope&gt;&lt;sys_update_name&gt;sc_cat_item_producer_59199e89c3b726107e68b41ed401313c&lt;/sys_update_name&gt;&lt;sys_updated_by&gt;system&lt;/sys_updated_by&gt;&lt;sys_updated_on&gt;2025-09-04 20:33:30&lt;/sys_updated_on&gt;&lt;table_name&gt;x_854636_b_board_clone_template_task&lt;/table_name&gt;&lt;taxonomy_topic/&gt;&lt;template/&gt;&lt;template_manager_roles/&gt;&lt;type&gt;item&lt;/type&gt;&lt;use_sc_layout&gt;true&lt;/use_sc_layout&gt;&lt;vendor/&gt;&lt;version&gt;37&lt;/version&gt;&lt;view/&gt;&lt;visible_bundle&gt;true&lt;/visible_bundle&gt;&lt;visible_guide&gt;true&lt;/visible_guide&gt;&lt;visible_standalone&gt;true&lt;/visible_standalone&gt;&lt;workflow/&gt;&lt;/sc_cat_item_producer&gt;&lt;sys_translated_text action="delete_multiple" query="documentkey=59199e89c3b726107e68b41ed401313c"/&gt;&lt;fx_price action="delete_multiple" query="id=59199e89c3b726107e68b41ed401313c"/&gt;&lt;fx_price action="INSERT_OR_UPDATE"&gt;&lt;amount&gt;0&lt;/amount&gt;&lt;currency display_value="USD"&gt;USD&lt;/currency&gt;&lt;field&gt;price&lt;/field&gt;&lt;id&gt;59199e89c3b726107e68b41ed401313c&lt;/id&gt;&lt;parent/&gt;&lt;reference_amount&gt;0&lt;/reference_amount&gt;&lt;reference_currency display_value="USD"&gt;USD&lt;/reference_currency&gt;&lt;sys_created_by&gt;system&lt;/sys_created_by&gt;&lt;sys_created_on&gt;2025-09-03 20:28:11&lt;/sys_created_on&gt;&lt;sys_id&gt;19199e89c3b726107e68b41ed401313f&lt;/sys_id&gt;&lt;sys_mod_count&gt;0&lt;/sys_mod_count&gt;&lt;sys_updated_by&gt;system&lt;/sys_updated_by&gt;&lt;sys_updated_on&gt;2025-09-03 20:28:11&lt;/sys_updated_on&gt;&lt;table&gt;sc_cat_item_producer&lt;/table&gt;&lt;type&gt;calculated&lt;/type&gt;&lt;/fx_price&gt;&lt;/record_update&gt;</payload>
        <payload_hash>1930187030</payload_hash>
        <record_name>Azure Synapse Analytics workspace</record_name>
        <reverted_from/>
        <source>e3d37109c3c2d2107e68b41ed40131d7</source>
        <source_table>sys_update_set</source_table>
        <state>previous</state>
        <sys_created_by>system</sys_created_by>
        <sys_created_on>2025-09-04 20:33:30</sys_created_on>
        <sys_id>7ce3a711c3f3a6107e68b41ed40131d9</sys_id>
        <sys_mod_count>0</sys_mod_count>
        <sys_recorded_at>199166f33da0000001</sys_recorded_at>
        <sys_updated_by>system</sys_updated_by>
        <sys_updated_on>2025-09-04 20:33:30</sys_updated_on>
        <type>Record Producer</type>
        <update_guid>b0e3a711f9f3a610b1c9eca9052b31d9</update_guid>
        <update_guid_history>b0e3a711f9f3a610b1c9eca9052b31d9:1930187030,3ce3a7110bf3a61007a0193be3dbf3c6:-335413342,b8e3a71121f3a61004cdfe618f732fb9:-1023656049,bce3a711a7f3a6102b661543fa90f1ad:790518320,f8e3a7112df3a61059d44bf1754d1595:-1690274607,7ce3a7118ef3a61084e2f0b1788a7b88:123899762,70e3a711bef3a6109608a9c6a6de9b76:1938074131,64e3a711f8f3a6107d58acec7dc63063:-1099762711,a0e3a71130f3a610eaed373c0f1b5644:714411658,ece3a7116ff3a6102759f84fb1f13c24:-1766381269,e0e3a71193f3a6101c8e314f9d634112:47793100,20e36711b7f3a6104819a3b16f5888f3:1861967469,24e36711d6f3a610d00921bb689488e0:-618825458,18e367116bf3a610dfde0dbf272ba7cd:1195348911,1ce3671179f3a610a950d36ac2f35eba:-1285444016,10e36711f3f3a610606a1bfb9c2552a8:528730353,d4e367112ff3a610c3f2541cac848696:-1952062574,98e367110ff3a610dfa905099a888b84:-694932120,c619de8906b7261087a1e9da1d8e559a:1119242249,0e19de8966b726100ae0a7c5a82dae88:-1361550678,8619de89d2b72610d3bb9612959ffe77:452623691,4619de8954b7261083ee8f2341941466:-2028169236,7919de89fcb7261017dcc9fc937f9855:-213994867,f919de8953b726105093e0a1d98d5b38:1600179502,7919de898fb7261065bb34989054fe28:-880613425,7519de899bb726107cff5cc91c1a4e0c:933560944,7d199e89e5b72610f2791e3611b601fc:-1547231983,f1199e89b8b726107570a90155d977e1:2043133611,ad199e89f2b72610eb2b60fff5528ec5:-437659316,55199e89e1b72610e1ffc723a2473d9e:1376515053,59199e89dfb72610a7bcc41f45c39384:-1104277874,15199e89f9b7261058a43f35ef2e037b:709896495,55199e890ab72610edbfaa8eb3c56271:-1770896432,19199e8920b72610837d16698ca41f67:43277937,59199e890ab726106b3be01d7a56ed53:1857452306,95199e8952b72610194bfb23cdc44355:11571839,91199e8916b72610f7707216c1153f4c:-266160771</update_guid_history>
    </sys_update_version>
    <sys_metadata_delete action="INSERT_OR_UPDATE">
        <sys_audit_delete display_value="Azure Synapse Analytics workspace">30e3a711c3f3a6107e68b41ed40131dd</sys_audit_delete>
        <sys_class_name>sys_metadata_delete</sys_class_name>
        <sys_created_by>system</sys_created_by>
        <sys_created_on>2025-09-04 20:33:30</sys_created_on>
        <sys_db_object display_value="" name="sc_cat_item_producer">sc_cat_item_producer</sys_db_object>
        <sys_id>26a3f86422c24ab0871f4379b1c42990</sys_id>
        <sys_metadata>59199e89c3b726107e68b41ed401313c</sys_metadata>
        <sys_mod_count>0</sys_mod_count>
        <sys_name>Azure Synapse Analytics workspace</sys_name>
        <sys_package display_value="Brainboard" source="x_854636_b_board">7062797e832822103e53f065eeaad32b</sys_package>
        <sys_parent display_value="Clone Template Task">9a7fd028c37f22107e68b41ed40131af</sys_parent>
        <sys_policy/>
        <sys_scope display_value="Brainboard">7062797e832822103e53f065eeaad32b</sys_scope>
        <sys_scope_delete display_value="">01c08e3452ee4472b472fb7397ff8e84</sys_scope_delete>
        <sys_update_name>sc_cat_item_producer_59199e89c3b726107e68b41ed401313c</sys_update_name>
        <sys_update_version display_value="sc_cat_item_producer_59199e89c3b726107e68b41ed401313c">7ce3a711c3f3a6107e68b41ed40131d9</sys_update_version>
        <sys_updated_by>system</sys_updated_by>
        <sys_updated_on>2025-09-04 20:33:30</sys_updated_on>
    </sys_metadata_delete>
</record_update>
